cenit_manager.py
printer.py
cenit_manager-0.0.4.data/data/cenit_manager
cenit_manager-0.0.4.data/data/Scripts/cenit_manager
cenit_manager-0.0.4.dist-info/DESCRIPTION.rst
cenit_manager-0.0.4.dist-info/METADATA
cenit_manager-0.0.4.dist-info/RECORD
cenit_manager-0.0.4.dist-info/WHEEL
cenit_manager-0.0.4.dist-info/entry_points.txt
cenit_manager-0.0.4.dist-info/metadata.json
cenit_manager-0.0.4.dist-info/top_level.txt
