Metadata-Version: 2.0
Name: cenit-manager
Version: 0.0.4
Summary: Mini Tool for Admin Cenit Account
Home-page: https://github.com/pypa/cenit_manager
Author: richar santiago Muñico Samaniego
Author-email: granlinux@gmail.com
License: UNKNOWN
Platform: UNKNOWN
Classifier: Programming Language :: Python :: 3
Classifier: License :: OSI Approved :: MIT License
Classifier: Operating System :: OS Independent
Requires-Python: >=3.5
Requires-Dist: argparse
Requires-Dist: requests
